<?xml version="1.0" encoding="UTF-8" standalone="no"?>
<!DOCTYPE tiles-definitions PUBLIC "-//Apache Software Foundation//DTD Tiles Configuration 2.1//EN" "http://tiles.apache.org/dtds/tiles-config_2_1.dtd">
<tiles-definitions>
    
    <definition extends="default" name="login/show">
        <put-attribute name="body" value="/WEB-INF/views/login/show.jspx"/>
    </definition>
    <definition extends="default" name="login/failure">
        <put-attribute name="body" value="/WEB-INF/views/login/failure.jspx"/>
    </definition>
    <definition extends="default" name="login/success">
        <put-attribute name="body" value="/WEB-INF/views/login/success.jspx"/>
    </definition>
    <definition extends="default" name="login/authfailure">
        <put-attribute name="body" value="/WEB-INF/views/login/authfailure.jspx"/>
    </definition>

    <definition extends="xrds" name="login/xdr">
        <put-attribute name="body" value="/WEB-INF/views/login/xdr.jspx"/>
    </definition>

    <definition extends="plain" name="login/associate">
        <put-attribute name="body" value="/WEB-INF/views/login/associate.jspx"/>
    </definition>
    
</tiles-definitions>
